torrotate/__init__.py
torrotate/config.py
torrotate/core.py
torrotate/utils.py
torrotate-0.1.0.dist-info/LICENSE
torrotate-0.1.0.dist-info/METADATA
torrotate-0.1.0.dist-info/WHEEL
torrotate-0.1.0.dist-info/top_level.txt
torrotate-0.1.0.dist-info/RECORD
