Metadata-Version: 2.2
Name: torrotate
Version: 0.1.0
Summary: A drop-in replacement for requests that routes through Tor with IP rotation
Author-email: Your Name <woprbotproducts@protonmail.com>
Project-URL: Homepage, https://github.com/pentestfunctions/torrotate
Project-URL: Bug Tracker, https://github.com/pentestfunctions/torrotate/issues
Classifier: Programming Language :: Python :: 3
Classifier: License :: OSI Approved :: MIT License
Classifier: Operating System :: OS Independent
Classifier: Development Status :: 4 - Beta
Classifier: Intended Audience :: Developers
Classifier: Topic :: Internet :: WWW/HTTP
Classifier: Topic :: Security :: Cryptography
Requires-Python: >=3.7
License-File: LICENSE
Requires-Dist: requests>=2.25.0
Requires-Dist: stem>=1.8.0
Dynamic: requires-python
